{
    "code": "1",
    "message": "操作成功",
    "object": {
        "table": {
            "fvc": {
                "pre|1-10": 1,
                "best|1-10": 1,
                "bestPre|1-10": 1
            },
            "fev1": {
                "pre|1-10": 1,
                "best|1-10": 1,
                "bestPre|1-10": 1
            },
            "pef": {
                "pre|1-10": 1,
                "best|1-10": 1,
                "bestPre|1-10": 1
            },
            "fef25": {
                "pre|1-10": 1,
                "best|1-10": 1,
                "bestPre|1-10": 1
            },
            "fef50": {
                "pre|1-10": 1,
                "best|1-10": 1,
                "bestPre|1-10": 1
            },
            "fef75": {
                "pre|1-10": 1,
                "best|1-10": 1,
                "bestPre|1-10": 1
            },
            "fef2575": {
                "pre|1-10": 1,
                "best|1-10": 1,
                "bestPre|1-10": 1
            }
        }
    }
}